pydantic_ai_guardrails/__init__.py
pydantic_ai_guardrails/__version__.py
pydantic_ai_guardrails/_config.py
pydantic_ai_guardrails/_context.py
pydantic_ai_guardrails/_guarded_agent.py
pydantic_ai_guardrails/_guardrails.py
pydantic_ai_guardrails/_parallel.py
pydantic_ai_guardrails/_results.py
pydantic_ai_guardrails/_telemetry.py
pydantic_ai_guardrails/_testing.py
pydantic_ai_guardrails/exceptions.py
pydantic_ai_guardrails/evals/__init__.py
pydantic_ai_guardrails/evals/_adapters.py
pydantic_ai_guardrails/evals/_context.py
pydantic_ai_guardrails/evals/_conversion.py
pydantic_ai_guardrails/evals/_testing.py
pydantic_ai_guardrails/evals/_wrapper.py
pydantic_ai_guardrails/guardrails/__init__.py
pydantic_ai_guardrails/guardrails/input/__init__.py
pydantic_ai_guardrails/guardrails/input/_blocked_keywords.py
pydantic_ai_guardrails/guardrails/input/_length.py
pydantic_ai_guardrails/guardrails/input/_pii.py
pydantic_ai_guardrails/guardrails/input/_prompt_injection.py
pydantic_ai_guardrails/guardrails/input/_rate_limit.py
pydantic_ai_guardrails/guardrails/input/_toxicity.py
pydantic_ai_guardrails/guardrails/output/__init__.py
pydantic_ai_guardrails/guardrails/output/_hallucination.py
pydantic_ai_guardrails/guardrails/output/_json.py
pydantic_ai_guardrails/guardrails/output/_length.py
pydantic_ai_guardrails/guardrails/output/_llm_judge.py
pydantic_ai_guardrails/guardrails/output/_no_refusals.py
pydantic_ai_guardrails/guardrails/output/_regex_match.py
pydantic_ai_guardrails/guardrails/output/_require_tool_use.py
pydantic_ai_guardrails/guardrails/output/_secrets.py
pydantic_ai_guardrails/guardrails/output/_tool_allowlist.py
pydantic_ai_guardrails/guardrails/output/_toxicity.py
pydantic_ai_guardrails/guardrails/output/_validate_tool_parameters.py
pydantic_ai_guardrails-0.2.1.dist-info/METADATA
pydantic_ai_guardrails-0.2.1.dist-info/WHEEL
pydantic_ai_guardrails-0.2.1.dist-info/licenses/LICENSE
pydantic_ai_guardrails-0.2.1.dist-info/RECORD
