Metadata-Version: 2.4
Name: pydantic-ai-guardrails
Version: 0.2.1
Summary: Production-ready guardrails for Pydantic AI with native integration patterns
Project-URL: Homepage, https://github.com/jagreehal/pydantic-ai-guardrails
Project-URL: Documentation, https://github.com/jagreehal/pydantic-ai-guardrails#readme
Project-URL: Repository, https://github.com/jagreehal/pydantic-ai-guardrails
Project-URL: Issues, https://github.com/jagreehal/pydantic-ai-guardrails/issues
Author-email: Jag Reehal <jag@jagreehal.com>
License: MIT
License-File: LICENSE
Keywords: ai-safety,ai-security,guardrails,input-validation,llm,output-validation,pii-detection,prompt-injection,pydantic-ai,validation
Classifier: Development Status :: 4 - Beta
Classifier: Intended Audience :: Developers
Classifier: License :: OSI Approved :: MIT License
Classifier: Programming Language :: Python :: 3
Classifier: Programming Language :: Python :: 3.10
Classifier: Programming Language :: Python :: 3.11
Classifier: Programming Language :: Python :: 3.12
Classifier: Programming Language :: Python :: 3.13
Classifier: Topic :: Scientific/Engineering :: Artificial Intelligence
Classifier: Topic :: Software Development :: Libraries :: Python Modules
Classifier: Typing :: Typed
Requires-Python: >=3.10
Requires-Dist: anyio>=4.0.0
Requires-Dist: pydantic-ai>=1.0.0
Requires-Dist: typing-extensions>=4.12.0
Provides-Extra: all
Requires-Dist: detoxify>=0.5.0; extra == 'all'
Requires-Dist: opentelemetry-api>=1.38.0; extra == 'all'
Requires-Dist: opentelemetry-sdk>=1.38.0; extra == 'all'
Requires-Dist: presidio-analyzer>=2.2.0; extra == 'all'
Requires-Dist: presidio-anonymizer>=2.2.0; extra == 'all'
Requires-Dist: pydantic-evals>=0.0.1; extra == 'all'
Requires-Dist: transformers>=4.30.0; extra == 'all'
Provides-Extra: dev
Requires-Dist: mypy>=1.18.0; extra == 'dev'
Requires-Dist: pytest-asyncio>=1.3.0; extra == 'dev'
Requires-Dist: pytest-cov>=7.0.0; extra == 'dev'
Requires-Dist: pytest>=9.0.0; extra == 'dev'
Requires-Dist: ruff>=0.14.0; extra == 'dev'
Provides-Extra: evals
Requires-Dist: pydantic-evals>=0.0.1; extra == 'evals'
Provides-Extra: pii-detection
Requires-Dist: presidio-analyzer>=2.2.0; extra == 'pii-detection'
Requires-Dist: presidio-anonymizer>=2.2.0; extra == 'pii-detection'
Provides-Extra: prompt-injection
Requires-Dist: transformers>=4.30.0; extra == 'prompt-injection'
Provides-Extra: telemetry
Requires-Dist: opentelemetry-api>=1.38.0; extra == 'telemetry'
Requires-Dist: opentelemetry-sdk>=1.38.0; extra == 'telemetry'
Provides-Extra: toxicity-detection
Requires-Dist: detoxify>=0.5.0; extra == 'toxicity-detection'
